example.py
script.py
pycrypto/__init__.py
pycrypto/crypto.py
pycrypto/info.py
pycrypto/price.py
pycrypto/util.py
cryptocli-0.0.1.dist-info/METADATA
cryptocli-0.0.1.dist-info/WHEEL
cryptocli-0.0.1.dist-info/entry_points.txt
cryptocli-0.0.1.dist-info/licenses/LICENSE
cryptocli-0.0.1.dist-info/RECORD
