Metadata-Version: 2.1
Name: cryptocli
Version: 0.0.1
Summary: A command line tool for pulling crypto data
Project-URL: Homepage, https://github.com/acrenwelge/cryptocli-python
Project-URL: Bug Tracker, https://github.com/acrenwelge/cryptocli-python/issues
Author-email: Andrew Crenwelge <andrewcrenwelge@gmail.com>
License-File: LICENSE
Classifier: License :: OSI Approved :: MIT License
Classifier: Operating System :: OS Independent
Classifier: Programming Language :: Python :: 3
Requires-Python: >=3.9
Requires-Dist: click
Requires-Dist: currency-symbols
Requires-Dist: importlib-metadata; python_version < '3.8'
Requires-Dist: prettytable
Requires-Dist: pycoingecko
